nuanced_mcp_server.py
iflow_mcp_nuanced_mcp-0.1.1.dist-info/METADATA
iflow_mcp_nuanced_mcp-0.1.1.dist-info/WHEEL
iflow_mcp_nuanced_mcp-0.1.1.dist-info/entry_points.txt
iflow_mcp_nuanced_mcp-0.1.1.dist-info/RECORD
