Metadata-Version: 2.4
Name: iflow-mcp_nuanced-mcp
Version: 0.1.1
Summary: MCP server expose nuanced.dev functionality
Requires-Python: >=3.13
Requires-Dist: mcp[cli]>=1.3.0
Requires-Dist: nuanced>=0.1.4
